peyo/__init__.py
peyo/api.py
peyo/builtins.py
peyo/dictionary.py
peyo/eyo.py
peyo/data/not_safe.txt
peyo/data/safe.txt
peyo-0.2.0.dist-info/licenses/LICENSE
peyo-0.2.0.dist-info/METADATA
peyo-0.2.0.dist-info/WHEEL
peyo-0.2.0.dist-info/top_level.txt
peyo-0.2.0.dist-info/RECORD
