Metadata-Version: 2.4
Name: peyo
Version: 0.2.0
Summary: Pure-Python port of eyo-kernel (dictionary-based yoification)
Author: Evgeny Ponomarev
License: MIT
Requires-Python: >=3.9
License-File: LICENSE
Dynamic: license-file
